{
    "configurations": [
        {
            "name": "Win32",
            "includePath": [
                "${workspaceFolder}/**",
                "${workspaceFolder}/lib/raylib-5.0_win64_msvc16/include",
                "${workspaceFolder}/lib/raylib-5.0-extra/include",
                "${workspaceFolder}/platform/engine/include",
                "${workspaceFolder}/platform/game/include"
            ],
            "defines": [
                "_DEBUG",
                "UNICODE",
                "_UNICODE"
            ],
            "windowsSdkVersion": "10.0.22621.0",
            "compilerPath": "cl.exe",
            "cStandard": "c17",
            "cppStandard": "c++20",
            "intelliSenseMode": "windows-msvc-x64"
        }
    ],
    "version": 4
}